adafruit_mmc56x3.py
adafruit_circuitpython_mmc56x3-1.0.14.dist-info/licenses/LICENSE
adafruit_circuitpython_mmc56x3-1.0.14.dist-info/METADATA
adafruit_circuitpython_mmc56x3-1.0.14.dist-info/WHEEL
adafruit_circuitpython_mmc56x3-1.0.14.dist-info/top_level.txt
adafruit_circuitpython_mmc56x3-1.0.14.dist-info/RECORD
